alu32_sv/alu32.sv
// alu32.sv
`timescale 1ns/1ps
import alu_pkg::*;

module alu32 (
  input  logic [31:0] a,
  input  logic [31:0] b,
  input  alu_op_t     op,

  output logic [31:0] y,
  output logic        z, // zero
  output logic        n, // negative
  output logic        c, // carry
  output logic        v  // overflow
);

  logic [32:0] tmp;

  always @(*) begin
    // default
    y = 32'd0;
    c = 1'b0;
    v = 1'b0;

    case (op)
      ALU_ADD: begin
        tmp = {1'b0, a} + {1'b0, b};
        y   = tmp[31:0];
        c   = tmp[32];
        v   = (~(a[31] ^ b[31])) & (y[31] ^ a[31]);
      end

      ALU_SUB: begin
        tmp = {1'b0, a} - {1'b0, b};
        y   = tmp[31:0];
        c   = ~tmp[32]; // no borrow
        v   = (a[31] ^ b[31]) & (y[31] ^ a[31]);
      end

      ALU_AND: y = a & b;
      ALU_OR : y = a | b;
      ALU_XOR: y = a ^ b;
      ALU_NOT: y = ~a;
      ALU_SLT: y = ($signed(a) < $signed(b)) ? 32'd1 : 32'd0;
      ALU_SLL: y = a << b[4:0];
      ALU_SRL: y = a >> b[4:0];

      default: y = 32'd0;
    endcase
  end

  // flags
  always @(*) begin
    z = (y == 32'd0);
    n = y[31];
  end

endmodule

alu32_sv/tb_alu32.sv
// tb_alu32.sv
`timescale 1ns/1ps
import alu_pkg::*;

module tb_alu32;

  logic [31:0] a, b;
  logic [3:0]  op_raw;
  alu_op_t     op;

  logic [31:0] y;
  logic z, n, c, v;

  alu32 dut (
    .a(a), .b(b), .op(op),
    .y(y), .z(z), .n(n), .c(c), .v(v)
  );

  task check;
    input [31:0] exp;
    begin
      if (y !== exp) begin
        $display("ERROR: a=%h b=%h op=%0d y=%h exp=%h", a, b, op, y, exp);
        $finish;
      end
    end
  endtask

  initial begin
    // Waveform dump (VCD)
    $dumpfile("tb_alu32.vcd");
    $dumpvars(0, tb_alu32);

    // ADD
    a = 10; b = 20; op = ALU_ADD; #1;
    check(30);

    // SUB
    a = 50; b = 8; op = ALU_SUB; #1;
    check(42);

    // AND
    a = 32'hF0F0; b = 32'h0FF0; op = ALU_AND; #1;
    check(32'h00F0);

    // OR
    op = ALU_OR; #1;
    check(32'hFFF0);

    // XOR
    op = ALU_XOR; #1;
    check(32'hFF00);

    // SLT
    a = -5; b = 3; op = ALU_SLT; #1;
    check(32'd1);

    // RANDOM TEST
    repeat (100) begin
      a = $random;
      b = $random;
      op_raw = $random % 9;
      op = alu_op_t'(op_raw);
      #1;
    end

    $display("ALL TESTS PASSED.");
    $finish;
  end

endmodule

alu32_sv/tb_alu32.vcd
$date
	Fri Dec 19 00:05:36 2025
$end
$version
	Icarus Verilog
$end
$timescale
	1ps
$end
$scope module tb_alu32 $end
$var wire 1 ! z $end
$var wire 32 " y [31:0] $end
$var wire 1 # v $end
$var wire 1 $ n $end
$var wire 1 % c $end
$var reg 32 & a [31:0] $end
$var reg 32 ' b [31:0] $end
$var reg 4 ( op [3:0] $end
$var reg 4 ) op_raw [3:0] $end
$scope module dut $end
$var wire 32 * a [31:0] $end
$var wire 32 + b [31:0] $end
$var wire 4 , op [3:0] $end
$var reg 1 % c $end
$var reg 1 $ n $end
$var reg 33 - tmp [32:0] $end
$var reg 1 # v $end
$var reg 32 . y [31:0] $end
$var reg 1 ! z $end
$upscope $end
$scope task check $end
$var reg 32 / exp [31:0] $end
$upscope $end
$upscope $end
$enddefinitions $end
$comment Show the parameter values. $end
$dumpall
$end
#0
$dumpvars
bx /
b11110 .
b11110 -
b0 ,
b10100 +
b1010 *
bx )
b0 (
b10100 '
b1010 &
0%
0$
0#
b11110 "
0!
$end
#1000
1%
b101010 -
b101010 "
b101010 .
b1 (
b1 ,
b1000 '
b1000 +
b110010 &
b110010 *
b11110 /
#2000
0%
b11110000 "
b11110000 .
b10 (
b10 ,
b111111110000 '
b111111110000 +
b1111000011110000 &
b1111000011110000 *
b101010 /
#3000
b1111111111110000 "
b1111111111110000 .
b11 (
b11 ,
b11110000 /
#4000
b1111111100000000 "
b1111111100000000 .
b100 (
b100 ,
b1111111111110000 /
#5000
b1 "
b1 .
b101 (
b101 ,
b11 '
b11 +
b11111111111111111111111111111011 &
b11111111111111111111111111111011 *
b1111111100000000 /
#6000
1$
b11010010100111101001001110100101 -
b11010010100111101001001110100101 "
b11010010100111101001001110100101 .
b0 (
b0 ,
b0 )
b11000000100010010101111010000001 '
b11000000100010010101111010000001 +
b10010000101010011010100100100 &
b10010000101010011010100100100 *
b1 /
#7000
0$
b1001110000011111010100110011100 "
b1001110000011111010100110011100 .
b1000 (
b1000 ,
b1000 )
b110101110010111101100001101 '
b110101110010111101100001101 +
b10110001111100000101011001100011 &
b10110001111100000101011001100011 *
#8000
1#
1%
b100111011111110011101011001110111 -
b111011111110011101011001110111 "
b111011111110011101011001110111 .
b0 (
b0 ,
b0 )
b10001001001101110101001000010010 '
b10001001001101110101001000010010 +
b10110010110000101000010001100101 &
b10110010110000101000010001100101 *
#9000
1$
0#
0%
b11111001001010000011001011110010 "
b11111001001010000011001011110010 .
b1000 (
b1000 ,
b1000 )
b111011001000111111000101110110 '
b111011001000111111000101110110 +
b110110101111100110100001101 &
b110110101111100110100001101 *
#10000
0$
b1110110110101000101 "
b1110110110101000101 .
b111 (
b111 ,
b111 )
b1000110001011011111011110001100 '
b1000110001011011111011110001100 +
b1110110110101000101011111101101 &
b1110110110101000101011111101101 *
#11000
1!
b0 "
b0 .
b1001 (
b1001 ,
b1001 )
b11100010111101111000010011000101 '
b11100010111101111000010011000101 +
b11100011001101110010010011000110 &
b11100011001101110010010011000110 *
#12000
b1110 (
b1110 ,
b1110 )
b10111011110100100111001001110111 '
b10111011110100100111001001110111 +
b1110010101011111111011111100101 &
b1110010101011111111011111100101 *
#13000
b1100 (
b1100 ,
b1100 )
b1111001001100000110100111110010 '
b1111001001100000110100111110010 +
b1000111111011001101101110001111 &
b1000111111011001101101110001111 *
#14000
1$
0!
b11100000000000000100101011000000 "
b11100000000000000100101011000000 .
b10 (
b10 ,
b10 )
b11100010110010100100111011000101 '
b11100010110010100100111011000101 +
b11110100000000000111101011101000 &
b11110100000000000111101011101000 *
#15000
0$
1!
b0 "
b0 .
b1010 (
b1010 ,
b1010 )
b10010110101010110101100000101101 '
b10010110101010110101100000101101 +
b11011110100011100010100010111101 &
b11011110100011100010100010111101 *
#16000
0!
b1001110000100001001110110011100 "
b1001110000100001001110110011100 .
b1000 (
b1000 ,
b1000 )
b101011100111000011100001010 '
b101011100111000011100001010 +
b10110001111011110110001001100011 &
b10110001111011110110001001100011 *
#17000
1!
b0 "
b0 .
b1001 (
b1001 ,
b1001 )
b1010101011110000100010110101010 '
b1010101011110000100010110101010 +
b10000011001000010000100100000 &
b10000011001000010000100100000 *
#18000
0!
1#
1%
b1010100101000111111011010101001 "
b1010100101000111111011010101001 .
b101010100101000111111011010101001 -
b0 (
b0 ,
b0 )
b10001001100000111011100000010011 '
b10001001100000111011100000010011 +
b11001011001000000011111010010110 &
b11001011001000000011111010010110 *
#19000
1$
b11011111010001111011001110111110 -
0#
0%
b11011111010001111011001110111110 "
b11011111010001111011001110111110 .
b110101100111111101110101101011 '
b110101100111111101110101101011 +
b10101001101001111101011001010011 &
b10101001101001111101011001010011 *
#20000
b11010010100000001000000000000000 "
b11010010100000001000000000000000 .
b110 (
b110 ,
b110 )
b11010111010101100011111010101110 '
b11010111010101100011111010101110 +
b10000001000101110100101000000010 &
b10000001000101110100101000000010 *
#21000
0$
b1 "
b1 .
b101 (
b101 ,
b101 )
b10001100001000100100100100011 '
b10001100001000100100100100011 +
b11100111110001010111001011001111 &
b11100111110001010111001011001111 *
#22000
1$
b10000100001100010000100000001000 "
b10000100001100010000100000001000 .
b10 (
b10 ,
b10 )
b10011110001100010100110000111100 '
b10011110001100010100110000111100 +
b11100101011100110000101011001010 &
b11100101011100110000101011001010 *
#23000
0$
1!
b0 "
b0 .
b1001 (
b1001 ,
b1001 )
b100000110001001011001101000001 '
b100000110001001011001101000001 +
b1000101001011100110000110001010 &
b1000101001011100110000110001010 *
#24000
0!
b1110111100101101110000011101111 "
b1110111100101101110000011101111 .
b101110111100101101110000011101111 -
b1 (
b1 ,
b1 )
b11000100100010100001001010001001 '
b11000100100010100001001010001001 +
b111100001000001111001101111000 &
b111100001000001111001101111000 *
#25000
b1011011000000100110010110 "
b1011011000000100110010110 .
b111 (
b111 ,
b111 )
b1100011010010111111100111000110 '
b1100011010010111111100111000110 +
b1011011000000100110010110110110 &
b1011011000000100110010110110110 *
#26000
1!
b0 "
b0 .
b1001 (
b1001 ,
b1001 )
b10101000011111101110100101010 '
b10101000011111101110100101010 +
b11011110011101010000001010111100 &
b11011110011101010000001010111100 *
#27000
0!
1#
1%
b1110101101001010111110011101100 "
b1110101101001010111110011101100 .
b1110101101001010111110011101100 -
b1 (
b1 ,
b1 )
b1000010111100100100000110000101 '
b1000010111100100100000110000101 +
b10111000100101111011111001110001 &
b10111000100101111011111001110001 *
#28000
1!
0#
0%
b0 "
b0 .
b1001 (
b1001 ,
b1001 )
b11101000001100011001100111010 '
b11101000001100011001100111010 +
b10011101110011000110000000111011 &
b10011101110011000110000000111011 *
#29000
0!
b10101010101 "
b10101010101 .
b111 (
b111 ,
b111 )
b1111000110110011001101111110001 '
b1111000110110011001101111110001 +
b1010101010100100101100010101 &
b1010101010100100101100010101 *
#30000
b10111000101101111110000101110 "
b10111000101101111110000101110 .
b100 (
b100 ,
b100 )
b100110001101011111101101001100 '
b100110001101011111101101001100 +
b110001001000110000011101100010 &
b110001001000110000011101100010 *
#31000
1!
b0 "
b0 .
b1010 (
b1010 ,
b1010 )
b1111100011011011010100111111000 '
b1111100011011011010100111111000 +
b1000111101110011010000110001111 &
b1000111101110011010000110001111 *
#32000
0!
b110000001110111010100101100000 "
b110000001110111010100101100000 .
b1000 (
b1000 ,
b1000 )
b10101110011111011001010001011100 '
b10101110011111011001010001011100 +
b11001111110001000101011010011111 &
b11001111110001000101011010011111 *
#33000
1!
b0 "
b0 .
b1001 (
b1001 ,
b1001 )
b10100100101011100011001001001001 '
b10100100101011100011001001001001 +
b1000100110111100011011110001001 &
b1000100110111100011011110001001 *
#34000
b101 (
b101 ,
b101 )
b10101000110001111111110001010001 '
b10101000110001111111110001010001 +
b11101011111111101100000011010111 &
b11101011111111101100000011010111 *
#35000
1$
0!
b11100111001111011111111111001110 "
b11100111001111011111111111001110 .
b11 (
b11 ,
b11 )
b11100001001011001100111011000010 '
b11100001001011001100111011000010 +
b110000111010111111100001100 &
b110000111010111111100001100 *
#36000
b11100000000000000000000000000000 "
b11100000000000000000000000000000 .
b110 (
b110 ,
b110 )
b11110111100101110110100111101 '
b11110111100101110110100111101 +
b10111011100000100101101001110111 &
b10111011100000100101101001110111 *
#37000
0$
b1000000111110101111111110000001 "
b1000000111110101111111110000001 .
b1000 (
b1000 ,
b1000 )
b110110111001011000000101101101 '
b110110111001011000000101101101 +
b10111111000001010000000001111110 &
b10111111000001010000000001111110 *
#38000
b111111010 "
b111111010 .
b111 (
b111 ,
b111 )
b11101001111010111111011011010011 '
b11101001111010111111011011010011 +
b1111110100101000111100011111 &
b1111110100101000111100011111 *
#39000
b1 "
b1 .
b101 (
b101 ,
b101 )
b101101110110100101100101011011 '
b101101110110100101100101011011 +
b10111100000101001000100001111000 &
b10111100000101001000100001111000 *
#40000
1$
b10110100111111110101110101101001 -
b10110100111111110101110101101001 "
b10110100111111110101110101101001 .
b0 (
b0 ,
b0 )
b10101000011001010111100101010 '
b10101000011001010111100101010 +
b10011111111100101010111000111111 &
b10011111111100101010111000111111 *
#41000
0$
1!
b0 "
b0 .
b1111 (
b1111 ,
b1111 )
b11000111000110100000110010001110 '
b11000111000110100000110010001110 +
b11000011001111110011100010000110 &
b11000011001111110011100010000110 *
#42000
0!
1%
b10000101100110101011000100000 "
b10000101100110101011000100000 .
b100010000101100110101011000100000 -
b0 (
b0 ,
b0 )
b10010011011111011011110000100110 '
b10010011011111011011110000100110 +
b1111101001101011001100111111010 &
b1111101001101011001100111111010 *
#43000
1!
0%
b0 "
b0 .
b1110 (
b1110 ,
b1110 )
b10010111100110011010100000101111 '
b10010111100110011010100000101111 +
b11010001100010111011010010100011 &
b11010001100010111011010010100011 *
#44000
1$
0!
b10001101111100010101101100011011 "
b10001101111100010101101100011011 .
b100 (
b100 ,
b100 )
b100010001010010000110101000100 '
b100010001010010000110101000100 +
b10101111110110000101011001011111 &
b10101111110110000101011001011111 *
#45000
0$
b10110100100100010110000101101 "
b10110100100100010110000101101 .
b11110011000010010001101011100110 '
b11110011000010010001101011100110 +
b11100101100110110011011011001011 &
b11100101100110110011011011001011 *
#46000
1!
b0 "
b0 .
b1101 (
b1101 ,
b1101 )
b11110110100000101110001011101101 '
b11110110100000101110001011101101 +
b10100110011111100000100101001 &
b10100110011111100000100101001 *
#47000
b1011 (
b1011 ,
b1011 )
b11011010100010101110001010110101 '
b11011010100010101110001010110101 +
b10110010100111111011011001100101 &
b10110010100111111011011001100101 *
#48000
0!
b1011111001000110001100010111101 "
b1011111001000110001100010111101 .
b1011111001000110001100010111101 -
b0 (
b0 ,
b0 )
b100010001100011111111101000100 '
b100010001100011111111101000100 +
b111100111100010001100101111001 &
b111100111100010001100101111001 *
#49000
b1001000010110010101000000000000 "
b1001000010110010101000000000000 .
b110 (
b110 ,
b110 )
b1010101111101101010110110101011 '
b1010101111101101010110110101011 +
b10101000010010000101100101010 &
b10101000010010000101100101010 *
#50000
1%
b100111011101111000110101001110110 -
b111011101111000110101001110110 "
b111011101111000110101001110110 .
b0 (
b0 ,
b0 )
b11001101010111101011110010011010 '
b11001101010111101011110010011010 +
b1101110010111011010110111011100 &
b1101110010111011010110111011100 *
#51000
1$
0%
b10110000110000000000000000000000 "
b10110000110000000000000000000000 .
b110 (
b110 ,
b110 )
b101011000011101110110101010110 '
b101011000011101110110101010110 +
b11100001111100010000001011000011 &
b11100001111100010000001011000011 *
#52000
0$
b1001100001001101000100110011000 "
b1001100001001101000100110011000 .
b1000 (
b1000 ,
b1000 )
b10000101001100010011010000001010 '
b10000101001100010011010000001010 +
b10110011110110010111011001100111 &
b10110011110110010111011001100111 *
#53000
1$
b11011000111000000001000110110001 -
b11011000111000000001000110110001 "
b11011000111000000001000110110001 .
b0 (
b0 ,
b0 )
b111100110100011000011101111001 '
b111100110100011000011101111001 +
b10011100000011101000101000111000 &
b10011100000011101000101000111000 *
#54000
1#
b10010100001110110001110100100111 -
b10010100001110110001110100100111 "
b10010100001110110001110100100111 .
b1001001110001100101110110010011 '
b1001001110001100101110110010011 +
b1001010011101001011111110010100 &
b1001010011101001011111110010100 *
#55000
0$
1!
0#
b0 "
b0 .
b1001 (
b1001 ,
b1001 )
b1101101110010110110100111011011 '
b1101101110010110110100111011011 +
b10101100101101111100101001011001 &
b10101100101101111100101001011001 *
#56000
b1100 (
b1100 ,
b1100 )
b10110110101001000010011001101101 '
b10110110101001000010011001101101 +
b1101100101100001011011111011001 &
b1101100101100001011011111011001 *
#57000
0!
b1111111001111110110110111111110 "
b1111111001111110110110111111110 .
b11 (
b11 ,
b11 )
b1011011000101110010110110110110 '
b1011011000101110010110110110110 +
b1100101001110110100100111001010 &
b1100101001110110100100111001010 *
#58000
b1 "
b1 .
b101 (
b101 ,
b101 )
b10011101001001101100000100 '
b10011101001001101100000100 +
b10100011000001110001101001000110 &
b10100011000001110001101001000110 *
#59000
b101011010001010010100110010110101 -
b1011010001010010100110010110101 "
b1011010001010010100110010110101 .
b1 (
b1 ,
b1 )
b11011010011011101011101010110100 '
b11011010011011101011101010110100 +
b110100100110000000011101101001 &
b110100100110000000011101101001 *
#60000
1!
b0 "
b0 .
b1011 (
b1011 ,
b1011 )
b10010110100100000000010000101101 '
b10010110100100000000010000101101 +
b10100011111001101100100101000 &
b10100011111001101100100101000 *
#61000
0!
b1101000101000110110001111010001 "
b1101000101000110110001111010001 .
b1000 (
b1000 ,
b1000 )
b10000100011101111110010000001000 '
b10000100011101111110010000001000 +
b10010111010111001001110000101110 &
b10010111010111001001110000101110 *
#62000
1!
b0 "
b0 .
b1001 (
b1001 ,
b1001 )
b10100100111100000011100101001 '
b10100100111100000011100101001 +
b11111110101001111010011011111101 &
b11111110101001111010011011111101 *
#63000
b11101101001101000000100011011010 '
b11101101001101000000100011011010 +
b1000011001101010110011110000110 &
b1000011001101010110011110000110 *
#64000
b10111000010101011100010001110000 '
b10111000010101011100010001110000 +
b110011010011101010011101100110 &
b110011010011101010011101100110 *
#65000
1$
0!
b10000000000000000000000000000000 "
b10000000000000000000000000000000 .
b110 (
b110 ,
b110 )
b101111001110101011001101011110 '
b101111001110101011001101011110 +
b1011101011100011001100110111010 &
b1011101011100011001100110111010 *
#66000
0$
1!
b0 "
b0 .
b1001 (
b1001 ,
b1001 )
b10001101001001001111011000011010 '
b10001101001001001111011000011010 +
b1101010100011100000010111010101 &
b1101010100011100000010111010101 *
#67000
0!
b1100110101011101001100011001101 "
b1100110101011101001100011001101 .
b1100110101011101001100011001101 -
b0 (
b0 ,
b0 )
b1001011001001110011011110010110 '
b1001011001001110011011110010110 +
b11011100001110110000100110111 &
b11011100001110110000100110111 *
#68000
1$
b11101110011010111011100111011100 -
b11101110011010111011100111011100 "
b11101110011010111011100111011100 .
b11011011010001100001101010110110 '
b11011011010001100001101010110110 +
b10011001001011001111100100110 &
b10011001001011001111100100110 *
#69000
b10010111110000111111011100000000 "
b10010111110000111111011100000000 .
b110 (
b110 ,
b110 )
b1000011011000010101011110000110 '
b1000011011000010101011110000110 +
b1101110010111110000111111011100 &
b1101110010111110000111111011100 *
#70000
0$
1!
b0 "
b0 .
b1110 (
b1110 ,
b1110 )
b11101101100011011000000011011011 '
b11101101100011011000000011011011 +
b111111010110101001101101111110 &
b111111010110101001101101111110 *
#71000
b1111 (
b1111 ,
b1111 )
b11111101001010001110010011111010 '
b11111101001010001110010011111010 +
b111100111011010010101101111001 &
b111100111011010010101101111001 *
#72000
1$
0!
b11011011111101010111100110110111 "
b11011011111101010111100110110111 .
b11 (
b11 ,
b11 )
b11010000111101010111100010100001 '
b11010000111101010111100010100001 +
b1011100101000000100100010111 &
b1011100101000000100100010111 *
#73000
0$
1%
b100100010111011111111000001000101 -
b100010111011111111000001000101 "
b100010111011111111000001000101 .
b0 (
b0 ,
b0 )
b1111010100011000101100111110101 '
b1111010100011000101100111110101 +
b10101000011000111001011001010000 &
b10101000011000111001011001010000 *
#74000
1!
0%
b0 "
b0 .
b1001 (
b1001 ,
b1001 )
b1100000101100010111010111000001 '
b1100000101100010111010111000001 +
b10010100100110101000101000101001 &
b10010100100110101000101000101001 *
#75000
0!
b110011111111100100101101100111 "
b110011111111100100101101100111 .
b1000 (
b1000 ,
b1000 )
b100101101100100111101101001011 '
b100101101100100111101101001011 +
b11001100000000011011010010011000 &
b11001100000000011011010010011000 *
#76000
1$
b11110111011100101111011011101110 "
b11110111011100101111011011101110 .
b11 (
b11 ,
b11 )
b11000101010100000001011010001010 '
b11000101010100000001011010001010 +
b11110110001000101110011011101100 &
b11110110001000101110011011101100 *
#77000
0$
1!
b0 "
b0 .
b1111 (
b1111 ,
b1111 )
b1010100100111101111110110101001 '
b1010100100111101111110110101001 +
b11010100010010111000000010101000 &
b11010100010010111000000010101000 *
#78000
1$
0!
b11111010010000000001111111110100 "
b11111010010000000001111111110100 .
b11111010010000000001111111110100 -
b0 (
b0 ,
b0 )
b11110011001101000110011011100110 '
b11110011001101000110011011100110 +
b111000010111011100100001110 &
b111000010111011100100001110 *
#79000
0$
1!
b0 "
b0 .
b1011 (
b1011 ,
b1011 )
b10101010110100001110100101010 '
b10101010110100001110100101010 +
b10101001011111011010100101010 &
b10101001011111011010100101010 *
#80000
b1100 (
b1100 ,
b1100 )
b10011100011011011110011000111000 '
b10011100011011011110011000111000 +
b1001111011101011111111110011110 &
b1001111011101011111111110011110 *
#81000
0!
b1100101011001111110011111001010 "
b1100101011001111110011111001010 .
b11 (
b11 ,
b11 )
b1100101001000110100010111001010 '
b1100101001000110100010111001010 +
b1100100011001001110001111001000 &
b1100100011001001110001111001000 *
#82000
b101010001111010010001101010100100 -
b1010001111010010001101010100100 "
b1010001111010010001101010100100 .
b1 (
b1 ,
b1 )
b11100011101101111010111011000111 '
b11100011101101111010111011000111 +
b110101101000001100100101101011 &
b110101101000001100100101101011 *
#83000
1$
b111111010111011101111000111110110 -
b11111010111011101111000111110110 "
b11111010111011101111000111110110 .
b1100010000101101010101111000100 '
b1100010000101101010101111000100 +
b1011101000001011001110110111010 &
b1011101000001011001110110111010 *
#84000
0$
b10010010010 "
b10010010010 .
b111 (
b111 ,
b111 )
b11011010001001101001101010110100 '
b11011010001001101001101010110100 +
b1001001001011111101001110010010 &
b1001001001011111101001110010010 *
#85000
1!
b0 "
b0 .
b1001 (
b1001 ,
b1001 )
b1111101011011011111010111111010 '
b1111101011011011111010111111010 +
b11000011001100111001000010000110 &
b11000011001100111001000010000110 *
#86000
b101 (
b101 ,
b101 )
b11011110110011100101111010111101 '
b11011110110011100101111010111101 +
b11001010001010010000100110010 &
b11001010001010010000100110010 *
#87000
0!
b1 "
b1 .
b1100101010000111100111111001010 '
b1100101010000111100111111001010 +
b11110010010010011010010011100100 &
b11110010010010011010010011100100 *
#88000
1!
b0 "
b0 .
b1110 (
b1110 ,
b1110 )
b1000111011001011010100110001110 '
b1000111011001011010100110001110 +
b11010000100101011010100010100001 &
b11010000100101011010100010100001 *
#89000
1$
0!
b10001110011000101000110100011100 "
b10001110011000101000110100011100 .
b110001110011000101000110100011100 -
b1 (
b1 ,
b1 )
b11110111100000101001000011101111 '
b11110111100000101001000011101111 +
b10000101111001010001111000001011 &
b10000101111001010001111000001011 *
#90000
0$
1!
b0 "
b0 .
b1001 (
b1001 ,
b1001 )
b10111010101100010100100001110101 '
b10111010101100010100100001110101 +
b11011011000001110010100110110 &
b11011011000001110010100110110 *
#91000
b1110 (
b1110 ,
b1110 )
b1000100011001011110011110001000 '
b1000100011001011110011110001000 +
b110101110011011011111101101011 &
b110101110011011011111101101011 *
#92000
0!
b110011011000000000000000000 "
b110011011000000000000000000 .
b110 (
b110 ,
b110 )
b1001001001111100100010110010010 '
b1001001001111100100010110010010 +
b1001101111100111000000110011011 &
b1001101111100111000000110011011 *
#93000
1$
b10111100001111000011111101111000 -
b10111100001111000011111101111000 "
b10111100001111000011111101111000 .
b0 (
b0 ,
b0 )
b100101101101110101111101001011 '
b100101101101110101111101001011 +
b10010110100001001110000000101101 &
b10010110100001001110000000101101 *
#94000
0$
b1110000111000110000100111100001 "
b1110000111000110000100111100001 .
b1000 (
b1000 ,
b1000 )
b110101100110000010100001101 '
b110101100110000010100001101 +
b10001111000111001111011000011110 &
b10001111000111001111011000011110 *
#95000
1!
b0 "
b0 .
b1010 (
b1010 ,
b1010 )
b1101000101011100001101111010001 '
b1101000101011100001101111010001 +
b1100000000111001110100011000 &
b1100000000111001110100011000 *
#96000
b101 (
b101 ,
b101 )
b10011101101111110110010000111011 '
b10011101101111110110010000111011 +
b10100000110000000010010001000001 &
b10100000110000000010010001000001 *
#97000
b1110 (
b1110 ,
b1110 )
b10101011000110010110001001010110 '
b10101011000110010110001001010110 +
b101001111011111110100101010011 &
b101001111011111110100101010011 *
#98000
1$
0!
b10000000011000101110001000000000 "
b10000000011000101110001000000000 .
b10 (
b10 ,
b10 )
b10000010011100111110001000000100 '
b10000010011100111110001000000100 +
b11110001011001101111101011100010 &
b11110001011001101111101011100010 *
#99000
b11110101100011110000000111101010 -
b11110101100011110000000111101010 "
b11110101100011110000000111101010 .
b0 (
b0 ,
b0 )
b1001001111100100110100010010 '
b1001001111100100110100010010 +
b11101100010100001011010011011000 &
b11101100010100001011010011011000 *
#100000
0$
1!
b0 "
b0 .
b1100 (
b1100 ,
b1100 )
b11110010100001111011011011100101 '
b11110010100001111011011011100101 +
b10011100100000010001001000111001 &
b10011100100000010001001000111001 *
#101000
0!
b1010101000110010101001010101010 "
b1010101000110010101001010101010 .
b100 (
b100 ,
b100 )
b1000000100100000101110110000001 '
b1000000100100000101110110000001 +
b10101100010010000111100101011 &
b10101100010010000111100101011 *
#102000
1!
b0 "
b0 .
b1101 (
b1101 ,
b1101 )
b1010000110101011111100110100001 '
b1010000110101011111100110100001 +
b10011101101010101010100100111 &
b10011101101010101010100100111 *
#103000
b1001 (
b1001 ,
b1001 )
b101100001011010010001101011000 '
b101100001011010010001101011000 +
b10000010001000100011101000000100 &
b10000010001000100011101000000100 *
#104000
1$
0!
b10010011100010000100011100100110 "
b10010011100010000100011100100110 .
b10010011100010000100011100100110 -
b0 (
b0 ,
b0 )
b10001001000110011011010000010010 '
b10001001000110011011010000010010 +
b1010011011101001001100010100 &
b1010011011101001001100010100 *
#105000
0$
1%
b100000011011011111011100000000110 -
b11011011111011100000000110 "
b11011011111011100000000110 .
b101010110000101101010101010101 '
b101010110000101101010101010101 +
b11011000101011001110001010110001 &
b11011000101011001110001010110001 *
